antsibull_docs/__init__.py
antsibull_docs/app_context.py
antsibull_docs/augment_docs.py
antsibull_docs/collection_config.py
antsibull_docs/collection_links.py
antsibull_docs/constants.py
antsibull_docs/env_variables.py
antsibull_docs/extra_docs.py
antsibull_docs/lint_collection_names.py
antsibull_docs/lint_extra_docs.py
antsibull_docs/lint_helpers.py
antsibull_docs/lint_plugin_docs.py
antsibull_docs/plugin_docs.py
antsibull_docs/process_docs.py
antsibull_docs/py.typed
antsibull_docs/rst_labels.py
antsibull_docs/rstcheck.py
antsibull_docs/ansible_output/__init__.py
antsibull_docs/ansible_output/load.py
antsibull_docs/ansible_output/process.py
antsibull_docs/ansible_output/replace.py
antsibull_docs/cli/__init__.py
antsibull_docs/cli/antsibull_docs.py
antsibull_docs/cli/doc_commands/__init__.py
antsibull_docs/cli/doc_commands/_build.py
antsibull_docs/cli/doc_commands/ansible_output.py
antsibull_docs/cli/doc_commands/collection.py
antsibull_docs/cli/doc_commands/collection_plugins.py
antsibull_docs/cli/doc_commands/current.py
antsibull_docs/cli/doc_commands/devel.py
antsibull_docs/cli/doc_commands/lint_docs.py
antsibull_docs/cli/doc_commands/plugin.py
antsibull_docs/cli/doc_commands/sphinx_init.py
antsibull_docs/cli/doc_commands/stable.py
antsibull_docs/data/__init__.py
antsibull_docs/data/ansible_2_10_routing.yml
antsibull_docs/data/docsite/__init__.py
antsibull_docs/data/docsite/ansible-docsite/collection-tombstone.rst.j2
antsibull_docs/data/docsite/ansible-docsite/list_of_callback_plugins.rst.j2
antsibull_docs/data/docsite/ansible-docsite/list_of_collections.rst.j2
antsibull_docs/data/docsite/ansible-docsite/list_of_collections_by_namespace.rst.j2
antsibull_docs/data/docsite/ansible-docsite/list_of_deprecations.rst.j2
antsibull_docs/data/docsite/ansible-docsite/list_of_env_variables.rst.j2
antsibull_docs/data/docsite/ansible-docsite/list_of_plugins.rst.j2
antsibull_docs/data/docsite/ansible-docsite/plugin-deprecation.rst.j2
antsibull_docs-2.24.0.dist-info/METADATA
antsibull_docs-2.24.0.dist-info/WHEEL
antsibull_docs-2.24.0.dist-info/entry_points.txt
antsibull_docs-2.24.0.dist-info/licenses/LICENSES/BSD-2-Clause.txt
antsibull_docs-2.24.0.dist-info/licenses/LICENSES/GPL-3.0-or-later.txt
antsibull_docs-2.24.0.dist-info/RECORD
