Metadata-Version: 2.4
Name: antsibull-docs
Version: 2.24.0
Summary: Tools for building Ansible documentation
Project-URL: Documentation, https://docs.ansible.com/projects/antsibull-docs/
Project-URL: Source code, https://github.com/ansible-community/antsibull-docs
Project-URL: Code of Conduct, https://docs.ansible.com/projects/ansible/latest/community/code_of_conduct.html
Project-URL: Bug tracker, https://github.com/ansible-community/antsibull-docs/issues
Project-URL: Changelog, https://github.com/ansible-community/antsibull-docs/tree/main/CHANGELOG.md
Author-email: Toshio Kuratomi <a.badger@gmail.com>, Felix Fontein <felix@fontein.de>
Maintainer-email: Felix Fontein <felix@fontein.de>, Maxwell G <maxwell@gtmx.me>
License-Expression: GPL-3.0-or-later
License-File: LICENSES/BSD-2-Clause.txt
License-File: LICENSES/GPL-3.0-or-later.txt
Classifier: Development Status :: 5 - Production/Stable
Classifier: Framework :: Ansible
Classifier: Intended Audience :: Developers
Classifier: Programming Language :: Python :: 3.9
Classifier: Programming Language :: Python :: 3.10
Classifier: Programming Language :: Python :: 3.11
Classifier: Programming Language :: Python :: 3.12
Classifier: Programming Language :: Python :: 3.13
Classifier: Programming Language :: Python :: 3.14
Classifier: Typing :: Typed
Requires-Python: >=3.9
Requires-Dist: aiohttp>=3.0.0
Requires-Dist: ansible-pygments
Requires-Dist: antsibull-changelog>=0.24.0
Requires-Dist: antsibull-core<4.0.0,>=3.5.0
Requires-Dist: antsibull-docs-parser<2.0.0,>=1.1.0
Requires-Dist: antsibull-docutils<2.0.0,>=1.3.0
Requires-Dist: antsibull-fileutils<2.0.0,>=1.3.0
Requires-Dist: asyncio-pool
Requires-Dist: docutils
Requires-Dist: jinja2>=3.0
Requires-Dist: packaging>=20.0
Requires-Dist: pydantic<3.0.0,>=2.0.0
Requires-Dist: pyyaml
Requires-Dist: rstcheck<7.0.0,>=3.0.0
Requires-Dist: semantic-version
Requires-Dist: sphinx
Provides-Extra: codeqa
Requires-Dist: flake8>=3.8.0; extra == 'codeqa'
Requires-Dist: pylint>=2.17.2; extra == 'codeqa'
Requires-Dist: reuse; extra == 'codeqa'
Provides-Extra: coverage
Requires-Dist: coverage[toml]; extra == 'coverage'
Provides-Extra: dev
Requires-Dist: ansible-core>=2.14.0; extra == 'dev'
Requires-Dist: asynctest; extra == 'dev'
Requires-Dist: black>=24; extra == 'dev'
Requires-Dist: cryptography; extra == 'dev'
Requires-Dist: flake8>=3.8.0; extra == 'dev'
Requires-Dist: isort; extra == 'dev'
Requires-Dist: mypy; extra == 'dev'
Requires-Dist: nox; extra == 'dev'
Requires-Dist: pylint>=2.17.2; extra == 'dev'
Requires-Dist: pytest; extra == 'dev'
Requires-Dist: pytest-asyncio>=0.12; extra == 'dev'
Requires-Dist: pytest-cov; extra == 'dev'
Requires-Dist: pytest-error-for-skips; extra == 'dev'
Requires-Dist: reuse; extra == 'dev'
Requires-Dist: types-aiofiles; extra == 'dev'
Requires-Dist: types-docutils; extra == 'dev'
Requires-Dist: types-html5lib; extra == 'dev'
Requires-Dist: types-pyyaml; extra == 'dev'
Provides-Extra: formatters
Requires-Dist: black>=24; extra == 'formatters'
Requires-Dist: isort; extra == 'formatters'
Provides-Extra: test
Requires-Dist: ansible-core>=2.14.0; extra == 'test'
Requires-Dist: asynctest; extra == 'test'
Requires-Dist: cryptography; extra == 'test'
Requires-Dist: pytest; extra == 'test'
Requires-Dist: pytest-asyncio>=0.12; extra == 'test'
Requires-Dist: pytest-cov; extra == 'test'
Requires-Dist: pytest-error-for-skips; extra == 'test'
Provides-Extra: typing
Requires-Dist: mypy; extra == 'typing'
Requires-Dist: pytest; extra == 'typing'
Requires-Dist: types-aiofiles; extra == 'typing'
Requires-Dist: types-docutils; extra == 'typing'
Requires-Dist: types-html5lib; extra == 'typing'
Requires-Dist: types-pyyaml; extra == 'typing'
